README.md
defend.py
setup.py
defend.egg-info/PKG-INFO
defend.egg-info/SOURCES.txt
defend.egg-info/dependency_links.txt
defend.egg-info/top_level.txt