Metadata-Version: 2.1
Name: defend
Version: 0.0.1
Summary: testing decorators
Home-page: https://github.com/selfquery/defend
Author: selfquery
Author-email: git@selfquery.dev
License: UNKNOWN
Platform: UNKNOWN
